alviss/__init__.py
alviss/quickloader.py
alviss/cli/__init__.py
alviss/cli/render/__init__.py
alviss/cli/render/main.py
alviss/cli/stubber/__init__.py
alviss/cli/stubber/main.py
alviss/loaders/__init__.py
alviss/loaders/autoloader.py
alviss/loaders/base.py
alviss/loaders/interface.py
alviss/loaders/jsonfile.py
alviss/loaders/yamlfile.py
alviss/renderers/__init__.py
alviss/renderers/static/__init__.py
alviss/renderers/static/_simple.py
alviss/renderers/static/interface.py
alviss/structs/__init__.py
alviss/structs/_base.py
alviss/structs/baseconfig.py
alviss/structs/cfgstub.py
alviss/structs/errors.py
alviss/structs/singletonconfig.py
alviss/stubber/__init__.py
alviss/stubber/stubmaker/__init__.py
alviss/stubber/stubmaker/_simple.py
alviss/stubber/stubmaker/_structs.py
alviss/stubber/stubmaker/interface.py
alviss/utils/__init__.py
alviss/utils/kwfields.py
alviss-3.3.0.dist-info/LICENSE
alviss-3.3.0.dist-info/METADATA
alviss-3.3.0.dist-info/WHEEL
alviss-3.3.0.dist-info/entry_points.txt
alviss-3.3.0.dist-info/top_level.txt
alviss-3.3.0.dist-info/RECORD
