Metadata-Version: 2.1
Name: alviss
Version: 3.3.0
Summary: Configuration file reader with some nifty bells and whistles added
Author-email: Thordur Matthiasson <thordurm@ccpgames.com>
License: MIT License
Project-URL: Homepage, https://github.com/ccpgames/alviss
Project-URL: Documentation, https://github.com/ccpgames/alviss/blob/main/README.md
Project-URL: Repository, https://github.com/ccpgames/alviss.git
Project-URL: Issues, https://github.com/ccpgames/alviss/issues
Project-URL: Changelog, https://github.com/ccpgames/alviss/blob/main/CHANGELOG.md
Keywords: config,configuration,json,yaml,tools,ccp,utils
Classifier: Development Status :: 5 - Production/Stable
Classifier: License :: OSI Approved :: MIT License
Classifier: Intended Audience :: Developers
Classifier: Programming Language :: Python
Classifier: Programming Language :: Python :: 3
Classifier: Programming Language :: Python :: 3.8
Classifier: Programming Language :: Python :: 3.9
Classifier: Programming Language :: Python :: 3.10
Classifier: Programming Language :: Python :: 3.11
Classifier: Programming Language :: Python :: 3.12
Classifier: Topic :: Software Development
Classifier: Topic :: Software Development :: Libraries
Classifier: Topic :: Software Development :: Libraries :: Python Modules
Classifier: Topic :: Utilities
License-File: LICENSE
Requires-Dist: PyYAML <7,>=6.0.1
Requires-Dist: ccptools <2,>=1.1
Provides-Extra: fidelius
Requires-Dist: fidelius <2,>=1.0 ; extra == 'fidelius'
